partftpy/TftpClient.py
partftpy/TftpContexts.py
partftpy/TftpPacketFactory.py
partftpy/TftpPacketTypes.py
partftpy/TftpServer.py
partftpy/TftpShared.py
partftpy/TftpStates.py
partftpy/__init__.py
partftpy/bin/__init__.py
partftpy/bin/partftpy_client.py
partftpy/bin/partftpy_server.py
partftpy-0.4.0.dist-info/LICENSE
partftpy-0.4.0.dist-info/METADATA
partftpy-0.4.0.dist-info/WHEEL
partftpy-0.4.0.dist-info/entry_points.txt
partftpy-0.4.0.dist-info/top_level.txt
partftpy-0.4.0.dist-info/RECORD
